ProgramizPythonJiaochengChuyiFix1/README.md
ProgramizPythonJiaochengChuyiFix1/__init__.py
ProgramizPythonJiaochengChuyiFix1/__main__.py
ProgramizPythonJiaochengChuyiFix1/file.epub
ProgramizPythonJiaochengChuyiFix1/index.html
ProgramizPythonJiaochengChuyiFix1/css/__init__.py
ProgramizPythonJiaochengChuyiFix1/css/annotations.css
ProgramizPythonJiaochengChuyiFix1/css/main.css
ProgramizPythonJiaochengChuyiFix1/css/normalize.css
ProgramizPythonJiaochengChuyiFix1/css/popup.css
ProgramizPythonJiaochengChuyiFix1/font/__init__.py
ProgramizPythonJiaochengChuyiFix1/font/fontello.eot
ProgramizPythonJiaochengChuyiFix1/font/fontello.svg
ProgramizPythonJiaochengChuyiFix1/font/fontello.ttf
ProgramizPythonJiaochengChuyiFix1/font/fontello.woff
ProgramizPythonJiaochengChuyiFix1/img/__init__.py
ProgramizPythonJiaochengChuyiFix1/img/annotator-glyph-sprite.png
ProgramizPythonJiaochengChuyiFix1/img/annotator-icon-sprite.png
ProgramizPythonJiaochengChuyiFix1/img/apple-touch-icon.png
ProgramizPythonJiaochengChuyiFix1/img/cancelfullscreen.png
ProgramizPythonJiaochengChuyiFix1/img/close.png
ProgramizPythonJiaochengChuyiFix1/img/fullscreen.png
ProgramizPythonJiaochengChuyiFix1/img/loader.gif
ProgramizPythonJiaochengChuyiFix1/img/menu-icon.png
ProgramizPythonJiaochengChuyiFix1/img/save.png
ProgramizPythonJiaochengChuyiFix1/img/saved.png
ProgramizPythonJiaochengChuyiFix1/img/settings-s.png
ProgramizPythonJiaochengChuyiFix1/img/settings.png
ProgramizPythonJiaochengChuyiFix1/img/star.png
ProgramizPythonJiaochengChuyiFix1/js/__init__.py
ProgramizPythonJiaochengChuyiFix1/js/epub.js
ProgramizPythonJiaochengChuyiFix1/js/epub.min.js
ProgramizPythonJiaochengChuyiFix1/js/epub.min.map
ProgramizPythonJiaochengChuyiFix1/js/hooks.min.js
ProgramizPythonJiaochengChuyiFix1/js/hooks.min.map
ProgramizPythonJiaochengChuyiFix1/js/reader.js
ProgramizPythonJiaochengChuyiFix1/js/reader.js.map
ProgramizPythonJiaochengChuyiFix1/js/reader.min.js
ProgramizPythonJiaochengChuyiFix1/js/reader.min.map
programiz_python_jiaocheng_chuyi_fix1-2025.3.24.0.dist-info/METADATA
programiz_python_jiaocheng_chuyi_fix1-2025.3.24.0.dist-info/WHEEL
programiz_python_jiaocheng_chuyi_fix1-2025.3.24.0.dist-info/entry_points.txt
programiz_python_jiaocheng_chuyi_fix1-2025.3.24.0.dist-info/top_level.txt
programiz_python_jiaocheng_chuyi_fix1-2025.3.24.0.dist-info/RECORD
